gbif_blocking_occurrences_download.py
gbif_blocking_occurrence_download-0.1.1.dist-info/LICENSE
gbif_blocking_occurrence_download-0.1.1.dist-info/WHEEL
gbif_blocking_occurrence_download-0.1.1.dist-info/METADATA
gbif_blocking_occurrence_download-0.1.1.dist-info/RECORD
