Metadata-Version: 2.1
Name: gbif-blocking-occurrence-download
Version: 0.1.1
Summary: 
Author: Nicolas Noé
Author-email: nicolas.noe@inbo.be
Requires-Python: >=3.8,<4.0
Classifier: Programming Language :: Python :: 3
Classifier: Programming Language :: Python :: 3.8
Classifier: Programming Language :: Python :: 3.9
Requires-Dist: pytest (>=6.2.4,<7.0.0)
Requires-Dist: requests (>=2.26.0,<3.0.0)
